{"tweets":[{"createdAt":"Sun Oct 01 19:04:04 +0000 2017","tweetId":"914566600392691713","tweet":"This is prob why we are the worst team in the NFL https://t.co/znF66ZCs1d","quoted_user":"thehill","quoted_tweet":"Miami Dolphins players kneel during national anthem for second week https://t.co/8RBXwN1e4h https://t.co/InFeh3I8fF","timestamp":1.506884644016E12,"quoteCount":0,"replyCount":0,"favoriteCount":0,"retweetCount":0,"user":{"userId":"2474203073","screenName":"anthonygmz17","followers":252,"friends":257,"numberOfTweets":1102},"topics":[],"mentioned_users":[],"hashtags":[],"comments":[{"user":"jcqb07","parentUser":"anthonygmz17","tweet":"RT @anthonygmz17: This is prob why we are the worst team in the NFL https://t.co/znF66ZCs1d","originalTweet":"This is prob why we are the worst team in the NFL https://t.co/znF66ZCs1d"},{"user":"fishercole20","parentUser":"anthonygmz17","tweet":"RT @anthonygmz17: This is prob why we are the worst team in the NFL https://t.co/znF66ZCs1d","originalTweet":"This is prob why we are the worst team in the NFL https://t.co/znF66ZCs1d"},{"user":"DixonWat7","parentUser":"anthonygmz17","tweet":"RT @anthonygmz17: This is prob why we are the worst team in the NFL https://t.co/znF66ZCs1d","originalTweet":"This is prob why we are the worst team in the NFL https://t.co/znF66ZCs1d"},{"user":"_dannyesinosa","parentUser":"anthonygmz17","tweet":"RT @anthonygmz17: This is prob why we are the worst team in the NFL https://t.co/znF66ZCs1d","originalTweet":"This is prob why we are the worst team in the NFL https://t.co/znF66ZCs1d"}],"isReply":false,"isRetweet":false,"isQuote":true,"hasComments":true}],"nodes":[{"index":0,"links":[],"score":4.0,"level":5,"title":"This is prob why we are the worst team in the NFL https://t.co/znF66ZCs1d","label":"anthonygmz17","duration":"","id":0,"color":"red","redditID":"anthonygmz17","isTrueCluster":"true","timestamp":1.506884644016E12,"simScore":0.0,"sentiment":"N/A"}],"sentiments":[],"links":[],"userNodes":[],"userLinks":[],"submissions":[],"sankeyNodes":[]}