{"tweets":[{"createdAt":"Oct 26, 2017 9:48:16 PM","tweetId":"923697822075011073","tweet":"RT @MikE_LLLLLL: Actress Sandra Bullock To Hillary Clinton: \"If You Don’t Like Our President You Can Leave And .. Do You Support Her? https…","retweeted_user":"MikE_LLLLLL","retweeted_tweet":"Actress Sandra Bullock To Hillary Clinton: \"If You Don’t Like Our President You Can Leave And .. Do You Support Her? https://t.co/lUPrae0yOg","retweeted_tweet_id":"923611083818127360","timestamp":1.509061696E12,"favoriteCount":0,"retweetCount":466,"user":{"userId":"721032336","screenName":"Baumery1","followers":1135,"friends":1544,"numberOfTweets":13833},"topics":["sandra bullock","hillary clinton","actress"],"comments":[{"user":"Baumery1","parentUser":"MikE_LLLLLL","tweet":"RT @MikE_LLLLLL: Actress Sandra Bullock To Hillary Clinton: \"If You Don’t Like Our President You Can Leave And .. Do You Support Her? https…","originalTweet":"Actress Sandra Bullock To Hillary Clinton: \"If You Don’t Like Our President You Can Leave And .. Do You Support Her? https://t.co/lUPrae0yOg","type":"retweet","sourceTimestamp":1.509061696E12,"targetTimestamp":1.509041016E12}],"isReply":false,"isRetweet":true,"isQuote":false,"isNormalTweet":false,"hasComments":true}],"nodes":[{"index":0,"links":[],"score":4.0,"level":5,"title":"RT @MikE_LLLLLL: Actress Sandra Bullock To Hillary Clinton: \"If You Don’t Like Our President You Can Leave And .. Do You Support Her? https…","label":"baumery1","duration":"","id":0,"color":"red","redditID":"Baumery1","isTrueCluster":"true","timestamp":1.509061696E12,"simScore":0.0,"sentiment":"N/A"}],"sentiments":[],"links":[],"userNodes":[],"userLinks":[],"submissions":[],"sankeyNodes":[]}