{"tweets":[{"createdAt":"Oct 26, 2017 10:34:39 PM","tweetId":"923709495116574721","tweet":"RT @MikE_LLLLLL: Actress Sandra Bullock To Hillary Clinton: \"If You Don’t Like Our President You Can Leave And .. Do You Support Her? https…","retweeted_user":"MikE_LLLLLL","retweeted_tweet":"Actress Sandra Bullock To Hillary Clinton: \"If You Don’t Like Our President You Can Leave And .. Do You Support Her? https://t.co/lUPrae0yOg","retweeted_tweet_id":"923611083818127360","timestamp":1.509064479E12,"favoriteCount":0,"retweetCount":466,"user":{"userId":"384094961","screenName":"BeachyKate69","followers":14247,"friends":7778,"numberOfTweets":191286},"topics":["sandra bullock","hillary clinton","actress"],"comments":[{"user":"BeachyKate69","parentUser":"MikE_LLLLLL","tweet":"RT @MikE_LLLLLL: Actress Sandra Bullock To Hillary Clinton: \"If You Don’t Like Our President You Can Leave And .. Do You Support Her? https…","originalTweet":"Actress Sandra Bullock To Hillary Clinton: \"If You Don’t Like Our President You Can Leave And .. Do You Support Her? https://t.co/lUPrae0yOg","type":"retweet","sourceTimestamp":1.509064479E12,"targetTimestamp":1.509041016E12}],"isReply":false,"isRetweet":true,"isQuote":false,"isNormalTweet":false,"hasComments":true}],"nodes":[{"index":0,"links":[],"score":4.0,"level":5,"title":"RT @MikE_LLLLLL: Actress Sandra Bullock To Hillary Clinton: \"If You Don’t Like Our President You Can Leave And .. Do You Support Her? https…","label":"beachykate69","duration":"","id":0,"color":"red","redditID":"BeachyKate69","isTrueCluster":"true","timestamp":1.509064479E12,"simScore":0.0,"sentiment":"N/A"}],"sentiments":[],"links":[],"userNodes":[],"userLinks":[],"submissions":[],"sankeyNodes":[]}