{"tweets":[{"createdAt":"Sun Oct 01 07:46:17 +0000 2017","tweetId":"914396032515092481","tweet":"Wow. This is just obscene.\n#TheResistance #ImpeachTrump #PuertoRico https://t.co/doCLpzP7T9","quoted_user":"yashar","quoted_tweet":"1. POTUS\u0027 campaign just sent out this solicitation for campaign funds via text-message to supporters. In the video he holds his hand over his heart while the national anthem plays. He\u0027s now using the anthem he says must be respected by NFL players for campaign fundraising. https://t.co/vTZNwIuQ7g","timestamp":1.506843977465E12,"quoteCount":0,"replyCount":0,"favoriteCount":0,"retweetCount":0,"user":{"userId":"786419903855157249","screenName":"candemex74","followers":2988,"friends":4333,"numberOfTweets":20151},"topics":[],"mentioned_users":[],"hashtags":["TheResistance","ImpeachTrump","PuertoRico"],"comments":[{"user":"DeliaMacD1","parentUser":"candemex74","tweet":"RT @candemex74: Wow. This is just obscene.\n#TheResistance #ImpeachTrump #PuertoRico https://t.co/doCLpzP7T9","originalTweet":"Wow. This is just obscene.\n#TheResistance #ImpeachTrump #PuertoRico https://t.co/doCLpzP7T9"},{"user":"PingResist_z110","parentUser":"candemex74","tweet":"RT @candemex74: Wow. This is just obscene.\n#TheResistance #ImpeachTrump #PuertoRico https://t.co/doCLpzP7T9","originalTweet":"Wow. This is just obscene.\n#TheResistance #ImpeachTrump #PuertoRico https://t.co/doCLpzP7T9"},{"user":"MiamiPapers","parentUser":"candemex74","tweet":"RT @candemex74: Wow. This is just obscene.\n#TheResistance #ImpeachTrump #PuertoRico https://t.co/doCLpzP7T9","originalTweet":"Wow. This is just obscene.\n#TheResistance #ImpeachTrump #PuertoRico https://t.co/doCLpzP7T9"}],"isReply":false,"isRetweet":false,"isQuote":true,"hasComments":true}],"nodes":[{"index":0,"links":[],"score":4.0,"level":5,"title":"Wow. This is just obscene.\n#TheResistance #ImpeachTrump #PuertoRico https://t.co/doCLpzP7T9","label":"candemex74","duration":"","id":0,"color":"red","redditID":"candemex74","isTrueCluster":"true","timestamp":1.506843977465E12,"simScore":0.0,"sentiment":"N/A"}],"sentiments":[],"links":[],"userNodes":[],"userLinks":[],"submissions":[],"sankeyNodes":[]}