{"tweets":[{"createdAt":"Nov 1, 2017 5:10:18 AM","tweetId":"925620999898484736","replyToUserId":"910874659","tweet":"@RiceGum Someone had a #ricegang sign at a @WWE event lmaoo https://t.co/PRkDw75twM","replied_user":"RiceGum","replied_status_id":"925499936875016192","timestamp":1.509520218E12,"favoriteCount":5,"retweetCount":1,"user":{"userId":"1337159161","screenName":"cekoismith","followers":20,"friends":143,"numberOfTweets":433},"topics":[],"comments":[{"user":"whwjejje","parentUser":"cekoismith","tweet":"RT @cekoismith: @RiceGum Someone had a #ricegang sign at a @WWE event lmaoo https://t.co/PRkDw75twM","originalTweet":"@RiceGum Someone had a #ricegang sign at a @WWE event lmaoo https://t.co/PRkDw75twM","type":"retweet","sourceTimestamp":1.509583683E12,"targetTimestamp":1.509520218E12}],"isReply":true,"isRetweet":false,"isQuote":false,"isNormalTweet":false,"hasComments":true}],"nodes":[{"index":0,"links":[],"score":4.0,"level":5,"title":"@RiceGum Someone had a #ricegang sign at a @WWE event lmaoo https://t.co/PRkDw75twM","label":"cekoismith","duration":"","id":0,"color":"red","redditID":"cekoismith","isTrueCluster":"true","timestamp":1.509520218E12,"simScore":0.0,"sentiment":"N/A"}],"sentiments":[],"links":[],"userNodes":[],"userLinks":[],"submissions":[],"sankeyNodes":[]}