{"tweets":[{"createdAt":"Sun Oct 01 04:39:43 +0000 2017","tweetId":"914349080876331008","tweet":"I had to #wiki Corey Taylor #Anthem #anthemprotests https://t.co/ueG1fyknvG","quoted_user":"CWOGULA","quoted_tweet":"Corey Taylor Supports NFL Players Kneeling For The National Anthem - Rock Feed https://t.co/6jsu9o3RNI","timestamp":1.506832783322E12,"quoteCount":0,"replyCount":0,"favoriteCount":0,"retweetCount":0,"user":{"userId":"1676073468","screenName":"CWOGULA","followers":62,"friends":194,"numberOfTweets":736},"topics":["corey taylor","wiki","anthem"],"mentioned_users":[],"hashtags":["wiki","Anthem","anthemprotests"],"comments":[{"user":"CWOGULA","parentUser":"CWOGULA","tweet":"I had to #wiki Corey Taylor #Anthem #anthemprotests https://t.co/ueG1fyknvG","originalTweet":"I had to #wiki Corey Taylor #Anthem #anthemprotests https://t.co/ueG1fyknvG"}],"isReply":false,"isRetweet":false,"isQuote":true,"hasComments":true}],"nodes":[{"index":0,"links":[],"score":4.0,"level":5,"title":"I had to #wiki Corey Taylor #Anthem #anthemprotests https://t.co/ueG1fyknvG","label":"cwogula","duration":"","id":0,"color":"red","redditID":"CWOGULA","isTrueCluster":"true","timestamp":1.506832783322E12,"simScore":0.0,"sentiment":"N/A"}],"sentiments":[],"links":[],"userNodes":[],"userLinks":[],"submissions":[],"sankeyNodes":[]}