{"tweets":[{"createdAt":"Sun Oct 01 04:12:47 +0000 2017","tweetId":"914342305200345088","tweet":"?? https://t.co/dwUGyHes1w","quoted_user":"yashar","quoted_tweet":"1. POTUS\u0027 campaign just sent out this solicitation for campaign funds via text-message to supporters. In the video he holds his hand over his heart while the national anthem plays. He\u0027s now using the anthem he says must be respected by NFL players for campaign fundraising. https://t.co/vTZNwIuQ7g","timestamp":1.506831167875E12,"quoteCount":0,"replyCount":0,"favoriteCount":0,"retweetCount":0,"user":{"userId":"18684946","screenName":"davequast","followers":3444,"friends":3296,"numberOfTweets":49457},"topics":[],"mentioned_users":[],"hashtags":[],"comments":[{"user":"leighindy","parentUser":"davequast","tweet":"RT @davequast: ?? https://t.co/dwUGyHes1w","originalTweet":"?? https://t.co/dwUGyHes1w"}],"isReply":false,"isRetweet":false,"isQuote":true,"hasComments":true}],"nodes":[{"index":0,"links":[],"score":4.0,"level":5,"title":"?? https://t.co/dwUGyHes1w","label":"davequast","duration":"","id":0,"color":"red","redditID":"davequast","isTrueCluster":"true","timestamp":1.506831167875E12,"simScore":0.0,"sentiment":"N/A"}],"sentiments":[],"links":[],"userNodes":[],"userLinks":[],"submissions":[],"sankeyNodes":[]}