{"tweets":[{"createdAt":"Oct 31, 2017 10:50:17 PM","tweetId":"925525367967879168","replyToUserId":"4100627615","tweet":"@Bee_Sillva @acidp4nic Vai fumante","replied_user":"Bee_Sillva","replied_status_id":"925525130549350401","timestamp":1.509497417E12,"favoriteCount":0,"retweetCount":0,"user":{"userId":"849888950886031363","screenName":"lahgrs","followers":361,"friends":538,"numberOfTweets":3884},"topics":[],"comments":[{"user":"Bee_Sillva","parentUser":"lahgrs","tweet":"@lahgrs @acidp4nic Eu né","originalTweet":"@Bee_Sillva @acidp4nic Vai fumante","type":"reply","sourceTimestamp":1.509497451E12,"targetTimestamp":1.509497417E12}],"isReply":true,"isRetweet":false,"isQuote":false,"isNormalTweet":false,"hasComments":true}],"nodes":[{"index":0,"links":[],"score":4.0,"level":5,"title":"@Bee_Sillva @acidp4nic Vai fumante","label":"lahgrs","duration":"","id":0,"color":"red","redditID":"lahgrs","isTrueCluster":"true","timestamp":1.509497417E12,"simScore":0.0,"sentiment":"N/A"}],"sentiments":[],"links":[],"userNodes":[],"userLinks":[],"submissions":[],"sankeyNodes":[]}