{"tweets":[{"createdAt":"Mon Oct 02 00:39:09 +0000 2017","tweetId":"914650929508610050","tweet":"STAY over there - no one wants u back! Laughable, CLUELESS dimwits! https://t.co/80LVxgINOU","quoted_user":"fubaglady","quoted_tweet":"Three NFL players kneel for U.S. national anthem, stand for British anthem during Saints-Dolphins London game: https://t.co/IesqVHNuRv","timestamp":1.506904749644E12,"quoteCount":0,"replyCount":0,"favoriteCount":0,"retweetCount":0,"user":{"userId":"728653876489035776","screenName":"Lisa77720","followers":6794,"friends":7441,"numberOfTweets":32589},"topics":["clueless"],"mentioned_users":[],"hashtags":[],"comments":[{"user":"Mindy4110","parentUser":"Lisa77720","tweet":"RT @Lisa77720: Stand WITH HAND OVER HEART - will stand for nothing less! These LOSERS are helping BAND together Patriots - insurin… ","originalTweet":"STAY over there - no one wants u back! Laughable, CLUELESS dimwits! https://t.co/80LVxgINOU"},{"user":"vision835","parentUser":"Lisa77720","tweet":"RT @Lisa77720: With Hand Over Heart! https://t.co/NrxrIwSzUw","originalTweet":"STAY over there - no one wants u back! Laughable, CLUELESS dimwits! https://t.co/80LVxgINOU"}],"isReply":false,"isRetweet":false,"isQuote":true,"hasComments":true}],"nodes":[{"index":0,"links":[],"score":4.0,"level":5,"title":"STAY over there - no one wants u back! Laughable, CLUELESS dimwits! https://t.co/80LVxgINOU","label":"lisa77720","duration":"","id":0,"color":"red","redditID":"Lisa77720","isTrueCluster":"true","timestamp":1.506904749644E12,"simScore":0.0,"sentiment":"N/A"}],"sentiments":[],"links":[],"userNodes":[],"userLinks":[],"submissions":[],"sankeyNodes":[]}