{"tweets":[{"createdAt":"Mon Oct 02 02:11:18 +0000 2017","tweetId":"914674119240589312","tweet":"NFL teams show unity in response to anthem uproar https://t.co/WIY05AVbjb","timestamp":1.506910278507E12,"quoteCount":0,"replyCount":0,"favoriteCount":0,"retweetCount":0,"user":{"userId":"45381821","screenName":"Lnnie","followers":81305,"friends":70132,"numberOfTweets":82861},"topics":["anthem"],"mentioned_users":[],"hashtags":[],"comments":[{"user":"SandyDarity","parentUser":"Lnnie","tweet":"RT @Lnnie: NFL teams show unity in response to anthem uproar https://t.co/WIY05AVbjb","originalTweet":"NFL teams show unity in response to anthem uproar https://t.co/WIY05AVbjb"},{"user":"taina_hhk","parentUser":"Lnnie","tweet":"RT @Lnnie: NFL teams show unity in response to anthem uproar https://t.co/WIY05AVbjb","originalTweet":"NFL teams show unity in response to anthem uproar https://t.co/WIY05AVbjb"},{"user":"JoeFeagin","parentUser":"Lnnie","tweet":"RT @Lnnie: NFL teams show unity in response to anthem uproar https://t.co/WIY05AVbjb","originalTweet":"NFL teams show unity in response to anthem uproar https://t.co/WIY05AVbjb"},{"user":"bev_bowns","parentUser":"Lnnie","tweet":"RT @Lnnie: NFL teams show unity in response to anthem uproar https://t.co/WIY05AVbjb","originalTweet":"NFL teams show unity in response to anthem uproar https://t.co/WIY05AVbjb"}],"isReply":false,"isRetweet":false,"isQuote":false,"hasComments":true}],"nodes":[{"index":0,"links":[],"score":4.0,"level":5,"title":"NFL teams show unity in response to anthem uproar https://t.co/WIY05AVbjb","label":"lnnie","duration":"","id":0,"color":"red","redditID":"Lnnie","isTrueCluster":"true","timestamp":1.506910278507E12,"simScore":0.0,"sentiment":"N/A"}],"sentiments":[],"links":[],"userNodes":[],"userLinks":[],"submissions":[],"sankeyNodes":[]}