{"tweets":[{"createdAt":"Nov 1, 2017 7:03:48 PM","tweetId":"925830759675506689","replyToUserId":"2883880904","tweet":"@reis_carolinaa @acidp4nic Claro kkkkkkkk","replied_user":"reis_carolinaa","replied_status_id":"925830427981496321","timestamp":1.509570228E12,"favoriteCount":1,"retweetCount":0,"user":{"userId":"3331303881","screenName":"marimouraj","followers":762,"friends":653,"numberOfTweets":2606},"topics":["claro"],"comments":[{"user":"reis_carolinaa","parentUser":"marimouraj","tweet":"@marimouraj @acidp4nic Ainda te disse pra vc parar de fumar tá vendo? Eu já parei com a droga faz tempo","originalTweet":"@reis_carolinaa @acidp4nic Claro kkkkkkkk","type":"reply","sourceTimestamp":1.509570086E12,"targetTimestamp":1.509570228E12},{"user":"reis_carolinaa","parentUser":"marimouraj","tweet":"@marimouraj @acidp4nic Nem eu kkkkkkkk vamos morrer juntinhos cê sabe né?","originalTweet":"@reis_carolinaa @acidp4nic Claro kkkkkkkk","type":"reply","sourceTimestamp":1.509570149E12,"targetTimestamp":1.509570228E12}],"isReply":true,"isRetweet":false,"isQuote":false,"isNormalTweet":false,"hasComments":true}],"nodes":[{"index":0,"links":[],"score":4.0,"level":5,"title":"@reis_carolinaa @acidp4nic Claro kkkkkkkk","label":"marimouraj","duration":"","id":0,"color":"red","redditID":"marimouraj","isTrueCluster":"true","timestamp":1.509570228E12,"simScore":0.0,"sentiment":"N/A"}],"sentiments":[],"links":[],"userNodes":[],"userLinks":[],"submissions":[],"sankeyNodes":[]}