{"tweets":[{"createdAt":"Sun Oct 01 01:30:11 +0000 2017","tweetId":"914301382051745792","tweet":"With all disrespect, Fuck you!! https://t.co/espHwPADV0","quoted_user":"realDonaldTrump","quoted_tweet":"Very important that NFL players STAND tomorrow, and always, for the playing of our National Anthem. Respect our Flag and our Country!","timestamp":1.506821411036E12,"quoteCount":0,"replyCount":0,"favoriteCount":0,"retweetCount":0,"user":{"userId":"253369322","screenName":"MJnCBREEZY4LYFE","followers":1921,"friends":890,"numberOfTweets":126029},"topics":["fuck you"],"mentioned_users":[],"hashtags":[],"comments":[{"user":"BreezyMisha","parentUser":"MJnCBREEZY4LYFE","tweet":"RT @MJnCBREEZY4LYFE: With all disrespect, Fuck you!! https://t.co/espHwPADV0","originalTweet":"With all disrespect, Fuck you!! https://t.co/espHwPADV0"}],"isReply":false,"isRetweet":false,"isQuote":true,"hasComments":true}],"nodes":[{"index":0,"links":[],"score":4.0,"level":5,"title":"With all disrespect, Fuck you!! https://t.co/espHwPADV0","label":"mjncbreezy4lyfe","duration":"","id":0,"color":"red","redditID":"MJnCBREEZY4LYFE","isTrueCluster":"true","timestamp":1.506821411036E12,"simScore":0.0,"sentiment":"N/A"}],"sentiments":[],"links":[],"userNodes":[],"userLinks":[],"submissions":[],"sankeyNodes":[]}