{"tweets":[{"createdAt":"Sun Oct 01 18:00:43 +0000 2017","tweetId":"914550661458493441","tweet":"?????????? https://t.co/TeLqXpZSlz","quoted_user":"darrenrovell","quoted_tweet":"Last week, about 180 NFL players didn\u0027t stand for the National Anthem. This week? 11. https://t.co/L1NAIXKyZx","timestamp":1.506880843878E12,"quoteCount":0,"replyCount":0,"favoriteCount":0,"retweetCount":0,"user":{"userId":"3640650913","screenName":"Oil_Guns_Merica","followers":4882,"friends":2650,"numberOfTweets":19931},"topics":[],"mentioned_users":[],"hashtags":[],"comments":[{"user":"ThunderB","parentUser":"Oil_Guns_Merica","tweet":"RT @Oil_Guns_Merica: ?????????? https://t.co/TeLqXpZSlz","originalTweet":"?????????? https://t.co/TeLqXpZSlz"},{"user":"RussJensen5","parentUser":"Oil_Guns_Merica","tweet":"RT @Oil_Guns_Merica: ?????????? https://t.co/TeLqXpZSlz","originalTweet":"?????????? https://t.co/TeLqXpZSlz"},{"user":"joshuapchase","parentUser":"Oil_Guns_Merica","tweet":"RT @Oil_Guns_Merica: ?????????? https://t.co/TeLqXpZSlz","originalTweet":"?????????? https://t.co/TeLqXpZSlz"}],"isReply":false,"isRetweet":false,"isQuote":true,"hasComments":true}],"nodes":[{"index":0,"links":[],"score":4.0,"level":5,"title":"?????????? https://t.co/TeLqXpZSlz","label":"oil_guns_merica","duration":"","id":0,"color":"red","redditID":"Oil_Guns_Merica","isTrueCluster":"true","timestamp":1.506880843878E12,"simScore":0.0,"sentiment":"N/A"}],"sentiments":[],"links":[],"userNodes":[],"userLinks":[],"submissions":[],"sankeyNodes":[]}