{"tweets":[{"createdAt":"Nov 2, 2017 9:41:58 AM","tweetId":"926051757658054656","replyToUserId":"705569479384817664","tweet":"@joejohnson043 @Bhazor @PrisonPlanet He changed a lo of ambassadors...but not this one","replied_user":"joejohnson043","replied_status_id":"925925206446739456","timestamp":1.509622918E12,"favoriteCount":1,"retweetCount":0,"user":{"userId":"925160090512121856","screenName":"RonaldKDTrump","followers":23,"friends":92,"numberOfTweets":173},"topics":["prisonplanet"],"comments":[{"user":"joejohnson043","parentUser":"RonaldKDTrump","tweet":"@RonaldKDTrump @PrisonPlanet We didn\u0027t do it, unelected leftists judges did...","originalTweet":"@joejohnson043 @Bhazor @PrisonPlanet He changed a lo of ambassadors...but not this one","type":"reply","sourceTimestamp":1.509542951E12,"targetTimestamp":1.509622918E12},{"user":"joejohnson043","parentUser":"RonaldKDTrump","tweet":"@RonaldKDTrump @Bhazor @PrisonPlanet Romanians should hate EU as well! Don\u0027t let these Globalists loot your resourc… https://t.co/QT9AP8nVwx","originalTweet":"@joejohnson043 @Bhazor @PrisonPlanet He changed a lo of ambassadors...but not this one","type":"reply","sourceTimestamp":1.509583745E12,"targetTimestamp":1.509622918E12},{"user":"joejohnson043","parentUser":"RonaldKDTrump","tweet":"@RonaldKDTrump @Bhazor @PrisonPlanet Considering who put him there, I\u0027m not surprised...","originalTweet":"@joejohnson043 @Bhazor @PrisonPlanet He changed a lo of ambassadors...but not this one","type":"reply","sourceTimestamp":1.509583527E12,"targetTimestamp":1.509622918E12},{"user":"joejohnson043","parentUser":"RonaldKDTrump","tweet":"@RonaldKDTrump @Bhazor @PrisonPlanet He\u0027s pretty busy with the amount of swamp creatures in DC....","originalTweet":"@joejohnson043 @Bhazor @PrisonPlanet He changed a lo of ambassadors...but not this one","type":"reply","sourceTimestamp":1.509592746E12,"targetTimestamp":1.509622918E12},{"user":"joejohnson043","parentUser":"RonaldKDTrump","tweet":"@RonaldKDTrump @Bhazor @PrisonPlanet Well, keep telling people about him, eventually Trump will get the message.","originalTweet":"@joejohnson043 @Bhazor @PrisonPlanet He changed a lo of ambassadors...but not this one","type":"reply","sourceTimestamp":1.509630787E12,"targetTimestamp":1.509622918E12}],"isReply":true,"isRetweet":false,"isQuote":false,"isNormalTweet":false,"hasComments":true}],"nodes":[{"index":0,"links":[],"score":4.0,"level":5,"title":"@joejohnson043 @Bhazor @PrisonPlanet He changed a lo of ambassadors...but not this one","label":"ronaldkdtrump","duration":"","id":0,"color":"red","redditID":"RonaldKDTrump","isTrueCluster":"true","timestamp":1.509622918E12,"simScore":0.0,"sentiment":"N/A"}],"sentiments":[],"links":[],"userNodes":[],"userLinks":[],"submissions":[],"sankeyNodes":[]}