{"tweets":[{"createdAt":"Sun Oct 01 22:35:23 +0000 2017","tweetId":"914619780321234944","tweet":"#BoycottNFL #BoycottNFLSponsors https://t.co/dbtjpiDaN1","quoted_user":"FoxNews","quoted_tweet":"Poll: 47% say players\u0027 protests during National Anthem is the reason they\u0027ve watched fewer @NFL games. https://t.co/eHdmc5WMlq","timestamp":1.506897323099E12,"quoteCount":0,"replyCount":0,"favoriteCount":0,"retweetCount":0,"user":{"userId":"4267265183","screenName":"scotthwk62","followers":12259,"friends":7636,"numberOfTweets":70323},"topics":[],"mentioned_users":[],"hashtags":["BoycottNFL","BoycottNFLSponsors"],"comments":[{"user":"Charlot35060083","parentUser":"scotthwk62","tweet":"RT @scotthwk62: #BoycottNFL #BoycottNFLSponsors https://t.co/dbtjpiDaN1","originalTweet":"#BoycottNFL #BoycottNFLSponsors https://t.co/dbtjpiDaN1"},{"user":"tom_tsetung","parentUser":"scotthwk62","tweet":"RT @scotthwk62: #BoycottNFL #BoycottNFLSponsors https://t.co/KawM187xfJ","originalTweet":"#BoycottNFL #BoycottNFLSponsors https://t.co/dbtjpiDaN1"}],"isReply":false,"isRetweet":false,"isQuote":true,"hasComments":true}],"nodes":[{"index":0,"links":[],"score":4.0,"level":5,"title":"#BoycottNFL #BoycottNFLSponsors https://t.co/dbtjpiDaN1","label":"scotthwk62","duration":"","id":0,"color":"red","redditID":"scotthwk62","isTrueCluster":"true","timestamp":1.506897323099E12,"simScore":0.0,"sentiment":"N/A"}],"sentiments":[],"links":[],"userNodes":[],"userLinks":[],"submissions":[],"sankeyNodes":[]}