{"nodes":[{"index":0,"links":[],"score":4.0,"level":5,"title":"This morning, I received an email from someone who called Obama a Muslim.","label":"qgyh2","duration":"","id":0,"color":"red","redditID":"t3_75hfo","isTrueCluster":"true","timestamp":1.223328405E9,"simScore":0.0,"sentiment":"N/A"},{"index":1,"links":[0],"score":5.0,"level":5,"title":"saltyboatr","label":"As if being a Muslim is a bad thing.","duration":"","id":1,"color":"blue","redditID":"t1_c05qayc","isTrueCluster":"true","parentID":{"index":0,"links":[],"score":4.0,"level":5,"title":"This morning, I received an email from someone who called Obama a Muslim.","label":"qgyh2","duration":"","id":0,"color":"red","redditID":"t3_75hfo","isTrueCluster":"true","timestamp":1.223328405E9,"simScore":0.0,"sentiment":"N/A"},"timestamp":1.223337126E9,"simScore":0.6931785643100739,"sentiment":"  Negative"},{"index":2,"links":[1],"score":5.0,"level":5,"title":"ryanx27","label":"There are a lot of people (even on reddit) who would disagree with you. (I\u0027m not one of them)","duration":"","id":2,"color":"green","redditID":"t1_c05qcw0","isTrueCluster":"true","parentID":{"index":1,"links":[0],"score":5.0,"level":5,"title":"saltyboatr","label":"As if being a Muslim is a bad thing.","duration":"","id":1,"color":"blue","redditID":"t1_c05qayc","isTrueCluster":"true","parentID":{"index":0,"links":[],"score":4.0,"level":5,"title":"This morning, I received an email from someone who called Obama a Muslim.","label":"qgyh2","duration":"","id":0,"color":"red","redditID":"t3_75hfo","isTrueCluster":"true","timestamp":1.223328405E9,"simScore":0.0,"sentiment":"N/A"},"timestamp":1.223337126E9,"simScore":0.6931785643100739,"sentiment":"  Negative"},"timestamp":1.223343412E9,"simScore":0.7494791647833254,"sentiment":"  Negative"},{"index":3,"links":[2],"score":5.0,"level":5,"title":"SaltyBoatr","label":"Could it be \"small town values\" means \"we distrust outsiders\" to put it gently, or \"we are bigots\" to not say it gently?\n\nIn my case, I don\u0027t know a lot of Muslims, but I have known a few at work, and in every instance they have been hardworking good family loving individuals with wholesome moral values. ","duration":"","id":3,"color":"lightblue","redditID":"t1_c05qd7r","isTrueCluster":"true","parentID":{"index":2,"links":[1],"score":5.0,"level":5,"title":"ryanx27","label":"There are a lot of people (even on reddit) who would disagree with you. (I\u0027m not one of them)","duration":"","id":2,"color":"green","redditID":"t1_c05qcw0","isTrueCluster":"true","parentID":{"index":1,"links":[0],"score":5.0,"level":5,"title":"saltyboatr","label":"As if being a Muslim is a bad thing.","duration":"","id":1,"color":"blue","redditID":"t1_c05qayc","isTrueCluster":"true","parentID":{"index":0,"links":[],"score":4.0,"level":5,"title":"This morning, I received an email from someone who called Obama a Muslim.","label":"qgyh2","duration":"","id":0,"color":"red","redditID":"t3_75hfo","isTrueCluster":"true","timestamp":1.223328405E9,"simScore":0.0,"sentiment":"N/A"},"timestamp":1.223337126E9,"simScore":0.6931785643100739,"sentiment":"  Negative"},"timestamp":1.223343412E9,"simScore":0.7494791647833254,"sentiment":"  Negative"},"timestamp":1.223343412E9,"simScore":0.7305521949401332,"sentiment":"  Negative"},{"index":4,"links":[1],"score":5.0,"level":5,"title":"brendansheehan","label":"It\u0027s not a bad thing, but I\u0027d rather (even not bad things) be spread as truth, when they are untrue.","duration":"","id":4,"color":"green","redditID":"t1_c05qdvb","isTrueCluster":"true","parentID":{"index":1,"links":[0],"score":5.0,"level":5,"title":"saltyboatr","label":"As if being a Muslim is a bad thing.","duration":"","id":1,"color":"blue","redditID":"t1_c05qayc","isTrueCluster":"true","parentID":{"index":0,"links":[],"score":4.0,"level":5,"title":"This morning, I received an email from someone who called Obama a Muslim.","label":"qgyh2","duration":"","id":0,"color":"red","redditID":"t3_75hfo","isTrueCluster":"true","timestamp":1.223328405E9,"simScore":0.0,"sentiment":"N/A"},"timestamp":1.223337126E9,"simScore":0.6931785643100739,"sentiment":"  Negative"},"timestamp":1.223346374E9,"simScore":0.5359874971210956,"sentiment":"  Negative"},{"index":5,"links":[0],"score":5.0,"level":5,"title":"penguinfeather","label":"My step-grandfather sends me the obama-is-a-muslim forwards all the time. I have tried multiple times to get him to fact-check on snopes, to no avail. I also have a 50-some year old distant cousin who will no longer speak to me because I wrote back to 2 of her obama/muslim emails with the snopes pages discounting them. I cannot understand why someone would want to send out these emails w/o fact-checking first. It\u0027s my biggest pet peeve - the spreading of ignorance.","duration":"","id":5,"color":"blue","redditID":"t1_c05qich","isTrueCluster":"true","parentID":{"index":0,"links":[],"score":4.0,"level":5,"title":"This morning, I received an email from someone who called Obama a Muslim.","label":"qgyh2","duration":"","id":0,"color":"red","redditID":"t3_75hfo","isTrueCluster":"true","timestamp":1.223328405E9,"simScore":0.0,"sentiment":"N/A"},"timestamp":1.223360132E9,"simScore":0.8319928830349486,"sentiment":"  Negative"},{"index":6,"links":[0],"score":5.0,"level":5,"title":"sumgai","label":"Ignorance is bliss.","duration":"","id":6,"color":"blue","redditID":"t1_c05qaf6","isTrueCluster":"true","parentID":{"index":0,"links":[],"score":4.0,"level":5,"title":"This morning, I received an email from someone who called Obama a Muslim.","label":"qgyh2","duration":"","id":0,"color":"red","redditID":"t3_75hfo","isTrueCluster":"true","timestamp":1.223328405E9,"simScore":0.0,"sentiment":"N/A"},"timestamp":1.223335331E9,"simScore":0.8100357172744614,"sentiment":"  Positive"},{"index":7,"links":[0],"score":5.0,"level":5,"title":"kickstand","label":"I, for one, want an atheist President. As Bill Maher said on *The Daily Show* last week, I\u0027m hoping Obama is a secret atheist.\n\nBut I\u0027d be as OK with a Muslim president as a Christian president, as long as they are moderate in their belief. ","duration":"","id":7,"color":"blue","redditID":"t1_c05qdai","isTrueCluster":"true","parentID":{"index":0,"links":[],"score":4.0,"level":5,"title":"This morning, I received an email from someone who called Obama a Muslim.","label":"qgyh2","duration":"","id":0,"color":"red","redditID":"t3_75hfo","isTrueCluster":"true","timestamp":1.223328405E9,"simScore":0.0,"sentiment":"N/A"},"timestamp":1.223344581E9,"simScore":0.6821961786583184,"sentiment":"  Negative"}],"userNodes":[],"links":[{"source":1,"target":0,"weight":0.6931785643100739},{"source":2,"target":1,"weight":0.7494791647833254},{"source":3,"target":2,"weight":0.7305521949401332},{"source":4,"target":1,"weight":0.5359874971210956},{"source":5,"target":0,"weight":0.8319928830349486},{"source":6,"target":0,"weight":0.8100357172744614},{"source":7,"target":0,"weight":0.6821961786583184}],"userLinks":[],"submissions":[{"user":{"username":"hellovn100","modhash":"jvbw5a58t2b20ad1cf6676a9f0f966f7474feacbe76526174f","cookie":"43916988,2016-02-01T10:13:31,7d41f9ab63f3be827624a82b85a673182135f6f6","password":"111111"},"url":"http://www.opednews.com/articles/Those-Who-Call-Obama-A-Mus-by-Rob-Kall-081006-524.html","permalink":"/r/obama/comments/75hfo/this_morning_i_received_an_email_from_someone_who/?ref\u003dsearch_posts","author":"qgyh2","title":"This morning, I received an email from someone who called Obama a Muslim.","subreddit":"obama","subredditId":"t5_1a8ah","thumbnail":"","selftext":"","domain":"opednews.com","gilded":0,"commentCount":7,"score":31,"upVotes":31,"downVotes":0,"created":1.223328405E9,"createdUTC":1.223299605E9,"visited":false,"self":false,"saved":false,"edited":false,"stickied":false,"nsfw":false,"hidden":false,"clicked":false,"kind":"t3","identifier":"75hfo","fullName":"t3_75hfo"}],"sankeyNodes":[],"sentiments":[]}