{"tweets":[{"createdAt":"Oct 26, 2017 8:48:25 PM","tweetId":"923682758635016193","tweet":"https://t.co/hobXl1K8Wb","timestamp":1.509058105E12,"favoriteCount":3,"retweetCount":4,"user":{"userId":"774473491961749505","screenName":"mikesealyNC","followers":837,"friends":4489,"numberOfTweets":2369},"topics":[],"comments":[{"user":"Derrick69053606","parentUser":"mikesealyNC","tweet":"RT @mikesealyNC: https://t.co/hobXl1K8Wb","originalTweet":"https://t.co/hobXl1K8Wb","type":"retweet","sourceTimestamp":1.50915656E12,"targetTimestamp":1.509058105E12},{"user":"Isabel_Cavazos","parentUser":"mikesealyNC","tweet":"RT @mikesealyNC: https://t.co/hobXl1K8Wb","originalTweet":"https://t.co/hobXl1K8Wb","type":"retweet","sourceTimestamp":1.509156015E12,"targetTimestamp":1.509058105E12},{"user":"SeditionNOLA","parentUser":"mikesealyNC","tweet":"RT @mikesealyNC: https://t.co/hobXl1K8Wb","originalTweet":"https://t.co/hobXl1K8Wb","type":"retweet","sourceTimestamp":1.509154544E12,"targetTimestamp":1.509058105E12},{"user":"Kimberlee373","parentUser":"mikesealyNC","tweet":"RT @mikesealyNC: https://t.co/hobXl1K8Wb","originalTweet":"https://t.co/hobXl1K8Wb","type":"retweet","sourceTimestamp":1.50915425E12,"targetTimestamp":1.509058105E12},{"user":"Derrick69053606","parentUser":"mikesealyNC","tweet":"RT @mikesealyNC: https://t.co/hobXl1K8Wb","originalTweet":"https://t.co/hobXl1K8Wb","type":"retweet","sourceTimestamp":1.50915656E12,"targetTimestamp":1.509058105E12},{"user":"Isabel_Cavazos","parentUser":"mikesealyNC","tweet":"RT @mikesealyNC: https://t.co/hobXl1K8Wb","originalTweet":"https://t.co/hobXl1K8Wb","type":"retweet","sourceTimestamp":1.509156015E12,"targetTimestamp":1.509058105E12},{"user":"SeditionNOLA","parentUser":"mikesealyNC","tweet":"RT @mikesealyNC: https://t.co/hobXl1K8Wb","originalTweet":"https://t.co/hobXl1K8Wb","type":"retweet","sourceTimestamp":1.509154544E12,"targetTimestamp":1.509058105E12},{"user":"Kimberlee373","parentUser":"mikesealyNC","tweet":"RT @mikesealyNC: https://t.co/hobXl1K8Wb","originalTweet":"https://t.co/hobXl1K8Wb","type":"retweet","sourceTimestamp":1.50915425E12,"targetTimestamp":1.509058105E12}],"isReply":false,"isRetweet":false,"isQuote":false,"isNormalTweet":true,"hasComments":true}],"nodes":[{"index":0,"links":[],"score":5.0,"level":5,"title":"RT @mikesealyNC: https://t.co/hobXl1K8Wb","label":"RT @mikesealyNC: https://t.co/hobXl1K8Wb","duration":"","id":114,"color":"red","redditID":"derrick69053606","isTrueCluster":"true","timestamp":1.509058105E12,"simScore":0.0,"sentiment":"N/A","tweetType":"retweet"},{"index":1,"links":[],"score":5.0,"level":5,"title":"RT @mikesealyNC: https://t.co/hobXl1K8Wb","label":"RT @mikesealyNC: https://t.co/hobXl1K8Wb","duration":"","id":114,"color":"red","redditID":"isabel_cavazos","isTrueCluster":"true","timestamp":1.509058105E12,"simScore":0.0,"sentiment":"N/A","tweetType":"retweet"},{"index":2,"links":[],"score":5.0,"level":5,"title":"RT @mikesealyNC: https://t.co/hobXl1K8Wb","label":"RT @mikesealyNC: https://t.co/hobXl1K8Wb","duration":"","id":114,"color":"red","redditID":"seditionnola","isTrueCluster":"true","timestamp":1.509058105E12,"simScore":0.0,"sentiment":"N/A","tweetType":"retweet"},{"index":3,"links":[],"score":5.0,"level":5,"title":"RT @mikesealyNC: https://t.co/hobXl1K8Wb","label":"RT @mikesealyNC: https://t.co/hobXl1K8Wb","duration":"","id":114,"color":"red","redditID":"kimberlee373","isTrueCluster":"true","timestamp":1.509058105E12,"simScore":0.0,"sentiment":"N/A","tweetType":"retweet"},{"index":4,"links":[],"score":5.0,"level":5,"title":"RT @mikesealyNC: https://t.co/hobXl1K8Wb","label":"RT @mikesealyNC: https://t.co/hobXl1K8Wb","duration":"","id":114,"color":"red","redditID":"derrick69053606","isTrueCluster":"true","timestamp":1.509058105E12,"simScore":0.0,"sentiment":"N/A","tweetType":"retweet"},{"index":5,"links":[],"score":5.0,"level":5,"title":"RT @mikesealyNC: https://t.co/hobXl1K8Wb","label":"RT @mikesealyNC: https://t.co/hobXl1K8Wb","duration":"","id":114,"color":"red","redditID":"isabel_cavazos","isTrueCluster":"true","timestamp":1.509058105E12,"simScore":0.0,"sentiment":"N/A","tweetType":"retweet"},{"index":6,"links":[],"score":5.0,"level":5,"title":"RT @mikesealyNC: https://t.co/hobXl1K8Wb","label":"RT @mikesealyNC: https://t.co/hobXl1K8Wb","duration":"","id":114,"color":"red","redditID":"seditionnola","isTrueCluster":"true","timestamp":1.509058105E12,"simScore":0.0,"sentiment":"N/A","tweetType":"retweet"},{"index":7,"links":[],"score":5.0,"level":5,"title":"RT @mikesealyNC: https://t.co/hobXl1K8Wb","label":"RT @mikesealyNC: https://t.co/hobXl1K8Wb","duration":"","id":114,"color":"red","redditID":"kimberlee373","isTrueCluster":"true","timestamp":1.509058105E12,"simScore":0.0,"sentiment":"N/A","tweetType":"retweet"},{"index":0,"links":[],"score":4.0,"level":5,"title":"https://t.co/hobXl1K8Wb","label":"mikesealync","duration":"","id":0,"color":"red","redditID":"mikesealyNC","isTrueCluster":"true","timestamp":1.509058105E12,"simScore":0.0,"sentiment":"N/A"}],"sentiments":[],"links":[{"source":0,"target":0,"weight":1.0E-4},{"source":1,"target":0,"weight":1.0E-4},{"source":2,"target":0,"weight":1.0E-4},{"source":3,"target":0,"weight":1.0E-4},{"source":4,"target":0,"weight":1.0E-4},{"source":5,"target":0,"weight":1.0E-4},{"source":6,"target":0,"weight":1.0E-4},{"source":7,"target":0,"weight":1.0E-4}],"userNodes":[],"userLinks":[],"submissions":[],"sankeyNodes":[]}