{"tweets":[{"createdAt":"Oct 28, 2017 7:20:00 PM","tweetId":"924385284313067520","tweet":"Actress Sandra Bullock To Hillary Clinton: \"If You Don’t Like Our President You Can Leave And Never Come Back Again  https://t.co/ZkQLDURolX","timestamp":1.5092256E12,"favoriteCount":0,"retweetCount":1,"user":{"userId":"111642101","screenName":"Itaintmebabe7","followers":7384,"friends":7214,"numberOfTweets":35943},"topics":["sandra bullock","hillary clinton","actress"],"comments":[{"user":"SSLag47","parentUser":"Itaintmebabe7","tweet":"RT @Itaintmebabe7: Actress Sandra Bullock To Hillary Clinton: \"If You Don’t Like Our President You Can Leave And Never Come Back Again  htt…","originalTweet":"Actress Sandra Bullock To Hillary Clinton: \"If You Don’t Like Our President You Can Leave And Never Come Back Again  https://t.co/ZkQLDURolX","type":"retweet","sourceTimestamp":1.509226692E12,"targetTimestamp":1.5092256E12}],"isReply":false,"isRetweet":false,"isQuote":false,"isNormalTweet":true,"hasComments":true}],"nodes":[{"index":0,"links":[],"score":5.0,"level":5,"title":"RT @Itaintmebabe7: Actress Sandra Bullock To Hillary Clinton: \"If You Don’t Like Our President You Can Leave And Never Come Back Again  htt…","label":"RT @Itaintmebabe7: Actress Sandra Bullock To Hillary Clinton: \"If You Don’t Like Our President You Can Leave And Never Come Back Again  htt…","duration":"","id":36,"color":"red","redditID":"sslag47","isTrueCluster":"true","timestamp":1.5092256E12,"simScore":0.0,"sentiment":"N/A","tweetType":"retweet"},{"index":0,"links":[],"score":4.0,"level":5,"title":"Actress Sandra Bullock To Hillary Clinton: \"If You Don’t Like Our President You Can Leave And Never Come Back Again  https://t.co/ZkQLDURolX","label":"itaintmebabe7","duration":"","id":0,"color":"red","redditID":"Itaintmebabe7","isTrueCluster":"true","timestamp":1.5092256E12,"simScore":0.0,"sentiment":"N/A"}],"sentiments":[],"links":[{"source":0,"target":0,"weight":0.125}],"userNodes":[],"userLinks":[],"submissions":[],"sankeyNodes":[]}