{"tweets":[{"createdAt":"Oct 31, 2017 9:10:30 PM","tweetId":"925500253838741504","replyToUserId":"910874659","tweet":"@RiceGum hahahahaha i hate you","replied_user":"RiceGum","replied_status_id":"925499936875016192","timestamp":1.50949143E12,"favoriteCount":2,"retweetCount":0,"user":{"userId":"842061620872417280","screenName":"UnderscoreChris","followers":340,"friends":421,"numberOfTweets":2905},"topics":[],"comments":[{"user":"xDefyinlite","parentUser":"UnderscoreChris","tweet":"@UnderscoreChris @RiceGum Why u have notifications on then?","originalTweet":"@RiceGum hahahahaha i hate you","type":"reply","sourceTimestamp":1.509492187E12,"targetTimestamp":1.50949143E12}],"isReply":true,"isRetweet":false,"isQuote":false,"isNormalTweet":false,"hasComments":true}],"nodes":[{"index":0,"links":[],"score":4.0,"level":5,"title":"@RiceGum hahahahaha i hate you","label":"underscorechris","duration":"","id":0,"color":"red","redditID":"UnderscoreChris","isTrueCluster":"true","timestamp":1.50949143E12,"simScore":0.0,"sentiment":"N/A"}],"sentiments":[],"links":[],"userNodes":[],"userLinks":[],"submissions":[],"sankeyNodes":[]}